fix_protobuf_imports/__init__.py
fix_protobuf_imports/fix_protobuf_imports.py
fix_protobuf_imports-0.1.7.dist-info/entry_points.txt
fix_protobuf_imports-0.1.7.dist-info/LICENSE
fix_protobuf_imports-0.1.7.dist-info/WHEEL
fix_protobuf_imports-0.1.7.dist-info/METADATA
fix_protobuf_imports-0.1.7.dist-info/RECORD
