Metadata-Version: 2.1
Name: fix-protobuf-imports
Version: 0.1.7
Summary: A script to fix relative imports (from and to nested sub-directories) within compiled `*_pb2.py` Protobuf files.
License: MIT
Author: Markus Wegmann
Author-email: mw@technokrat.ch
Requires-Python: >=3.5,<4.0
Classifier: License :: OSI Approved :: MIT License
Classifier: Operating System :: OS Independent
Classifier: Programming Language :: Python :: 3
Classifier: Programming Language :: Python :: 3.5
Classifier: Programming Language :: Python :: 3.6
Classifier: Programming Language :: Python :: 3.7
Classifier: Programming Language :: Python :: 3.8
Classifier: Programming Language :: Python :: 3.9
Classifier: Programming Language :: Python :: 3.10
Classifier: Programming Language :: Python :: 3
Requires-Dist: click (>=8.1.3,<9.0.0)
